razemax/__init__.py
razemax/__version__.py
razemax/consumers.py
razemax/drivers.py
razemax/event_manager.py
razemax/exceptions.py
razemax/publisher.py
razemax-0.0.4.dist-info/LICENSE
razemax-0.0.4.dist-info/METADATA
razemax-0.0.4.dist-info/WHEEL
razemax-0.0.4.dist-info/top_level.txt
razemax-0.0.4.dist-info/RECORD
