Metadata-Version: 2.1
Name: razemax
Version: 0.0.4
Summary: SNS + SQS Communications made easy
Home-page: https://github.com/21buttons/razemax
Author: 21 Buttons APP S.L.
Author-email: jairo@21buttons.com
License: Apache License 2.0
Platform: UNKNOWN
Classifier: Development Status :: 5 - Production/Stable
Classifier: Intended Audience :: Developers
Classifier: Natural Language :: English
Classifier: Programming Language :: Python
Classifier: Programming Language :: Python :: 3.6
Classifier: Programming Language :: Python :: 3.7
Requires-Python: >=3.6.0
Requires-Dist: boto3
